talaria_client/__init__.py
talaria_client/client.py
talaria_client/encoder.py
talaria_client/encoder_test.py
talaria_client/talaria_pb2.py
talaria_client/talaria_pb2_grpc.py
TalariaClient-0.0.5.dist-info/METADATA
TalariaClient-0.0.5.dist-info/WHEEL
TalariaClient-0.0.5.dist-info/top_level.txt
TalariaClient-0.0.5.dist-info/RECORD
